neopdf/__init__.py
neopdf/neopdf.cpython-311-darwin.so
neopdf_hep-0.2.0.dist-info/METADATA
neopdf_hep-0.2.0.dist-info/WHEEL
neopdf_hep-0.2.0.dist-info/RECORD
