Metadata-Version: 2.4
Name: neopdf-hep
Version: 0.2.0
Classifier: Development Status :: 4 - Beta
Classifier: Intended Audience :: Science/Research
Classifier: License :: OSI Approved :: GNU General Public License v3 or later (GPLv3+)
Classifier: Natural Language :: English
Classifier: Operating System :: MacOS
Classifier: Operating System :: Microsoft :: Windows
Classifier: Operating System :: POSIX
Classifier: Programming Language :: Python :: 3 :: Only
Classifier: Programming Language :: Rust
Classifier: Topic :: Scientific/Engineering :: Physics
Requires-Dist: numpy>=1.16.0
Requires-Dist: pytest ; extra == 'test'
Requires-Dist: pytest-cov ; extra == 'test'
Provides-Extra: test
Requires-Python: >=3.7
Project-URL: homepage, https://github.com/Radonirinaunimi/neopdf
Project-URL: documentation, https://radonirinaunimi.github.io/neopdf/
Project-URL: changelog, https://github.com/Radonirinaunimi/neopdf/blob/master/CHANGELOG.md
